LinuxCaozuoxitongXiaCYuyanBianchengRumen007xiong/README.md
LinuxCaozuoxitongXiaCYuyanBianchengRumen007xiong/__init__.py
LinuxCaozuoxitongXiaCYuyanBianchengRumen007xiong/__main__.py
LinuxCaozuoxitongXiaCYuyanBianchengRumen007xiong/file.pdf
LinuxCaozuoxitongXiaCYuyanBianchengRumen007xiong/index.html
linux_caozuoxitong_xia_c_yuyan_biancheng_rumen_007xiong-2024.3.2.0.dist-info/METADATA
linux_caozuoxitong_xia_c_yuyan_biancheng_rumen_007xiong-2024.3.2.0.dist-info/WHEEL
linux_caozuoxitong_xia_c_yuyan_biancheng_rumen_007xiong-2024.3.2.0.dist-info/entry_points.txt
linux_caozuoxitong_xia_c_yuyan_biancheng_rumen_007xiong-2024.3.2.0.dist-info/top_level.txt
linux_caozuoxitong_xia_c_yuyan_biancheng_rumen_007xiong-2024.3.2.0.dist-info/RECORD
